classic/__init__.py
classic/http_auth/__init__.py
classic/http_auth/authentication.py
classic/http_auth/authorization.py
classic/http_auth/entities.py
classic/http_auth/errors.py
classic/http_auth/interfaces.py
classic/http_auth/spec.py
classic/http_auth/strategies/__init__.py
classic/http_auth/strategies/base.py
classic/http_auth/strategies/dummy.py
classic/http_auth/strategies/jwt_.py
classic/http_auth/strategies/keycloak_.py
classic_http_auth-0.2.1.dist-info/LICENSE
classic_http_auth-0.2.1.dist-info/METADATA
classic_http_auth-0.2.1.dist-info/WHEEL
classic_http_auth-0.2.1.dist-info/top_level.txt
classic_http_auth-0.2.1.dist-info/RECORD
