Metadata-Version: 2.1
Name: classic-http-auth
Version: 0.2.1
Summary: Authentication and authorization
Home-page: https://github.com/variasov/classic-http-auth
Author: Sergei Variasov, Arsen Abakarov
Author-email: variasov@gmail.com
License: UNKNOWN
Project-URL: Bug Tracker, https://github.com/variasov/classic-http-auth/issues
Platform: UNKNOWN
Classifier: Programming Language :: Python :: 3.7
Classifier: License :: OSI Approved :: MIT License
Classifier: Operating System :: OS Independent
Classifier: Development Status :: 4 - Beta
Requires-Python: >=3.7
Provides-Extra: dev
License-File: LICENSE
